MANIFEST.in
README.rst
setup.py
cell_tree2d/__init__.py
cell_tree2d/cell_tree2d.c
cell_tree2d/cell_tree2d.cpp
cell_tree2d/cell_tree2d.html
cell_tree2d/cell_tree2d.pyd
cell_tree2d/cell_tree2d.pyx
cell_tree2d.egg-info/PKG-INFO
cell_tree2d.egg-info/SOURCES.txt
cell_tree2d.egg-info/dependency_links.txt
cell_tree2d.egg-info/pbr.json
cell_tree2d.egg-info/requires.txt
cell_tree2d.egg-info/top_level.txt
cell_tree2d/test/__init__.py
cell_tree2d/test/test_cell_tree2d.py
cell_tree2d/test/test_quad_grid.py
cell_tree2d/test/__init__.py
cell_tree2d/test/test_cell_tree2d.py
cell_tree2d/test/test_quad_grid.py
src/cell_tree2d.cpp
src/cell_tree2d.h
src/testmain.cpp