Metadata-Version: 1.1
Name: cell-tree2d
Version: 0.3.0
Summary: Python wrappers around Cell-Tree 2D spatial index
Home-page: https://github.com/NOAA-ORR-ERD
Author: Jay Hennen
Author-email: jay.hennen@noaa.gov
License: Public Domain
Platform: UNKNOWN
Classifier: Development Status :: 4 - Beta
Classifier: License :: Public Domain
Classifier: Intended Audience :: Developers
Classifier: Intended Audience :: Science/Research
Classifier: Operating System :: OS Independent
Classifier: Programming Language :: C++
Classifier: Programming Language :: Cython
Classifier: Programming Language :: Python :: 2 :: Only
Classifier: Programming Language :: Python :: Implementation :: CPython
Classifier: Topic :: Utilities
Classifier: Topic :: Scientific/Engineering
Classifier: Topic :: Scientific/Engineering :: Visualization
